lionpride/__init__.py
lionpride/errors.py
lionpride/protocols.py
lionpride/py.typed
lionpride/core/__init__.py
lionpride/core/_utils.py
lionpride/core/broadcaster.py
lionpride/core/element.py
lionpride/core/event.py
lionpride/core/eventbus.py
lionpride/core/flow.py
lionpride/core/graph.py
lionpride/core/node.py
lionpride/core/pile.py
lionpride/core/processor.py
lionpride/core/progression.py
lionpride/libs/__init__.py
lionpride/libs/concurrency/__init__.py
lionpride/libs/concurrency/_cancel.py
lionpride/libs/concurrency/_errors.py
lionpride/libs/concurrency/_patterns.py
lionpride/libs/concurrency/_primitives.py
lionpride/libs/concurrency/_priority_queue.py
lionpride/libs/concurrency/_resource_tracker.py
lionpride/libs/concurrency/_run_async.py
lionpride/libs/concurrency/_task.py
lionpride/libs/concurrency/_utils.py
lionpride/libs/schema_handlers/__init__.py
lionpride/libs/schema_handlers/_breakdown_pydantic_annotation.py
lionpride/libs/schema_handlers/_minimal_yaml.py
lionpride/libs/schema_handlers/_schema_to_model.py
lionpride/libs/schema_handlers/_typescript.py
lionpride/libs/string_handlers/__init__.py
lionpride/libs/string_handlers/_extract_json.py
lionpride/libs/string_handlers/_fuzzy_json.py
lionpride/libs/string_handlers/_string_similarity.py
lionpride/libs/string_handlers/_to_num.py
lionpride/ln/__init__.py
lionpride/ln/_async_call.py
lionpride/ln/_fuzzy_match.py
lionpride/ln/_fuzzy_validate.py
lionpride/ln/_hash.py
lionpride/ln/_json_dump.py
lionpride/ln/_lazy_init.py
lionpride/ln/_list_call.py
lionpride/ln/_to_dict.py
lionpride/ln/_to_list.py
lionpride/ln/_utils.py
lionpride/operations/__init__.py
lionpride/operations/builder.py
lionpride/operations/flow.py
lionpride/operations/node.py
lionpride/operations/registry.py
lionpride/operations/operate/__init__.py
lionpride/operations/operate/act.py
lionpride/operations/operate/communicate.py
lionpride/operations/operate/factory.py
lionpride/operations/operate/generate.py
lionpride-1.0.0a12.dist-info/METADATA
lionpride-1.0.0a12.dist-info/WHEEL
lionpride-1.0.0a12.dist-info/licenses/LICENSE
lionpride-1.0.0a12.dist-info/RECORD
