Metadata-Version: 2.4
Name: lionpride
Version: 1.0.0a12
Summary: The kernel layer for production AI agents - protocol-based, type-safe, zero framework lock-in
Project-URL: Homepage, https://github.com/khive-ai/lionpride
Project-URL: Documentation, https://github.com/khive-ai/lionpride/blob/main/README.md
Project-URL: Repository, https://github.com/khive-ai/lionpride
Project-URL: Issues, https://github.com/khive-ai/lionpride/issues
Project-URL: Changelog, https://github.com/khive-ai/lionpride/blob/main/CHANGELOG.md
Author-email: HaiyangLi <quantocean.li@gmail.com>
License: Apache-2.0
License-File: LICENSE
Keywords: agents,ai,async,llm,multi-agent,orchestration,protocols,type-safety
Classifier: Development Status :: 3 - Alpha
Classifier: Intended Audience :: Developers
Classifier: License :: OSI Approved :: Apache Software License
Classifier: Programming Language :: Python :: 3
Classifier: Programming Language :: Python :: 3.11
Classifier: Programming Language :: Python :: 3.12
Classifier: Programming Language :: Python :: 3.13
Classifier: Programming Language :: Python :: 3.14
Classifier: Topic :: Scientific/Engineering :: Artificial Intelligence
Classifier: Topic :: Software Development :: Libraries :: Python Modules
Classifier: Typing :: Typed
Requires-Python: >=3.11
Requires-Dist: anyio>=4.7.0
Requires-Dist: httpx>=0.27.0
Requires-Dist: orjson>=3.10.0
Requires-Dist: pydantic>=2.10.0
Requires-Dist: python-dotenv>=1.2.1
Requires-Dist: tiktoken>=0.8.0
Provides-Extra: all
Requires-Dist: aioboto3>=12.0.0; extra == 'all'
Requires-Dist: aiosqlite>=0.19.0; extra == 'all'
Requires-Dist: asyncpg>=0.29.0; extra == 'all'
Requires-Dist: datamodel-code-generator>=0.25.0; extra == 'all'
Requires-Dist: fastmcp>=2.13.0; extra == 'all'
Requires-Dist: mcp>=1.23.0; extra == 'all'
Requires-Dist: rapidfuzz>=3.9.0; extra == 'all'
Requires-Dist: sqlalchemy[asyncio]>=2.0.0; extra == 'all'
Requires-Dist: urllib3>=2.6.0; extra == 'all'
Provides-Extra: fuzzy
Requires-Dist: rapidfuzz>=3.9.0; extra == 'fuzzy'
Provides-Extra: log-all
Requires-Dist: aioboto3>=12.0.0; extra == 'log-all'
Requires-Dist: aiosqlite>=0.19.0; extra == 'log-all'
Requires-Dist: asyncpg>=0.29.0; extra == 'log-all'
Requires-Dist: sqlalchemy[asyncio]>=2.0.0; extra == 'log-all'
Requires-Dist: urllib3>=2.6.0; extra == 'log-all'
Provides-Extra: log-postgres
Requires-Dist: asyncpg>=0.29.0; extra == 'log-postgres'
Requires-Dist: sqlalchemy[asyncio]>=2.0.0; extra == 'log-postgres'
Provides-Extra: log-s3
Requires-Dist: aioboto3>=12.0.0; extra == 'log-s3'
Requires-Dist: urllib3>=2.6.0; extra == 'log-s3'
Provides-Extra: log-sqlite
Requires-Dist: aiosqlite>=0.19.0; extra == 'log-sqlite'
Provides-Extra: mcp
Requires-Dist: fastmcp>=2.13.0; extra == 'mcp'
Requires-Dist: mcp>=1.23.0; extra == 'mcp'
Provides-Extra: schema-gen
Requires-Dist: datamodel-code-generator>=0.25.0; extra == 'schema-gen'
